mseep_playwright_server-0.1.4.dist-info/licenses/LICENSE
playwright_server/__init__.py
playwright_server/server.py
mseep_playwright_server-0.1.4.dist-info/METADATA
mseep_playwright_server-0.1.4.dist-info/WHEEL
mseep_playwright_server-0.1.4.dist-info/entry_points.txt
mseep_playwright_server-0.1.4.dist-info/top_level.txt
mseep_playwright_server-0.1.4.dist-info/RECORD
